hpcc_i_spark/__init__.py
hpcc_i_spark/cli.py
hpcc_i_spark/find_record_structure.py
hpcc_i_spark/get_content.py
hpcc_i_spark-0.1.1.dist-info/DESCRIPTION.rst
hpcc_i_spark-0.1.1.dist-info/METADATA
hpcc_i_spark-0.1.1.dist-info/RECORD
hpcc_i_spark-0.1.1.dist-info/WHEEL
hpcc_i_spark-0.1.1.dist-info/metadata.json
hpcc_i_spark-0.1.1.dist-info/top_level.txt
