Metadata-Version: 2.0
Name: hpcc-i-spark
Version: 0.1.1
Summary: This package can be used to connect to any hpcc cluster and use the data
Home-page: https://github.com/vivekaxl/hpcc_i_spark
Author: Vivek Nair
Author-email: vivekaxl@gmail.com
License: MIT
Keywords: hpcc_converter
Platform: UNKNOWN
Classifier: Development Status :: 2 - Pre-Alpha
Classifier: Intended Audience :: Developers
Classifier: License :: OSI Approved :: MIT License
Classifier: Natural Language :: English
Classifier: Programming Language :: Python :: 2.7
Requires-Dist: ujson
Requires-Dist: xmltodict
